dfdatetime/__init__.py
dfdatetime/apfs_time.py
dfdatetime/cocoa_time.py
dfdatetime/decorators.py
dfdatetime/definitions.py
dfdatetime/delphi_date_time.py
dfdatetime/dotnet_datetime.py
dfdatetime/factory.py
dfdatetime/fake_time.py
dfdatetime/fat_date_time.py
dfdatetime/filetime.py
dfdatetime/golang_time.py
dfdatetime/hfs_time.py
dfdatetime/interface.py
dfdatetime/java_time.py
dfdatetime/ole_automation_date.py
dfdatetime/posix_time.py
dfdatetime/precisions.py
dfdatetime/rfc2579_date_time.py
dfdatetime/semantic_time.py
dfdatetime/serializer.py
dfdatetime/systemtime.py
dfdatetime/time_elements.py
dfdatetime/uuid_time.py
dfdatetime/webkit_time.py
dfdatetime-20231205.dist-info/ACKNOWLEDGEMENTS
dfdatetime-20231205.dist-info/AUTHORS
dfdatetime-20231205.dist-info/LICENSE
dfdatetime-20231205.dist-info/METADATA
dfdatetime-20231205.dist-info/README
dfdatetime-20231205.dist-info/WHEEL
dfdatetime-20231205.dist-info/top_level.txt
dfdatetime-20231205.dist-info/RECORD
