Metadata-Version: 2.1
Name: dfdatetime
Version: 20231205
Summary: Digital Forensics date and time (dfDateTime).
Home-page: https://github.com/log2timeline/dfdatetime
Maintainer: Log2Timeline maintainers
Maintainer-email: log2timeline-maintainers@googlegroups.com
License: Apache License, Version 2.0
Classifier: Development Status :: 3 - Alpha
Classifier: Programming Language :: Python
Requires-Python: >=3.7
License-File: ACKNOWLEDGEMENTS
License-File: AUTHORS
License-File: LICENSE
License-File: README
